LICENSE.txt
MANIFEST.in
README.md
pyproject.toml
tox.ini
docs/api.rst
docs/code-of-conduct.md
docs/conf.py
docs/contributing.md
docs/getting-started.md
docs/index.rst
docs/requirements.txt
docs/_static/css/custom.css
docs/how-to/use-python-library.md
src/collins_dictionary_api_client.egg-info/PKG-INFO
src/collins_dictionary_api_client.egg-info/SOURCES.txt
src/collins_dictionary_api_client.egg-info/dependency_links.txt
src/collins_dictionary_api_client.egg-info/entry_points.txt
src/collins_dictionary_api_client.egg-info/requires.txt
src/collins_dictionary_api_client.egg-info/top_level.txt
src/danoan/dictionaries/collins/__init__.py
src/danoan/dictionaries/collins/cli/__init__.py
src/danoan/dictionaries/collins/cli/cli.py
src/danoan/dictionaries/collins/core/__init__.py
src/danoan/dictionaries/collins/core/api.py
src/danoan/dictionaries/collins/core/model.py
tests/conftest.py
tests/cli/test_cli.py
tests/integration/core/api/test_api.py