Metadata-Version: 2.1
Name: collins-dictionary-api-client
Version: 0.1.0
Summary: Client to the Collins dictionary API
Author-email: Daniel Martins Antunes <danoan2008@gmail.com>
License: MIT License
Project-URL: Documentation, https://danoan.github.io/collins-dictionary-api-client
Project-URL: Issues, https://github.com/danoan/collins-dictionary-api-client/issues
Project-URL: Source, https://github.com/danoan/collins-dictionary-api-client
Classifier: Development Status :: 4 - Beta
Classifier: Programming Language :: Python
Classifier: Programming Language :: Python :: 3.8
Classifier: Programming Language :: Python :: Implementation :: PyPy
Requires-Python: >=3.8
License-File: LICENSE.txt
Requires-Dist: beautifulsoup4
Requires-Dist: lxml
Requires-Dist: requests
